[
  {
    "Id": 600001,
    "Desc": "七日签到第一天奖励",
    "Rate": 10000,
    "Team": 1000,
    "Type": 1,
    "Items": "[{\"id\":101,\"num\":100},{\"id\":110,\"num\":100}]",
    "AddData": ""
  },
  {
    "Id": 600002,
    "Desc": "七日签到第二天奖励",
    "Rate": 10000,
    "Team": 1001,
    "Type": 1,
    "Items": "[{\"id\":101,\"num\":200},{\"id\":110,\"num\":200}]",
    "AddData": ""
  },
  {
    "Id": 600003,
    "Desc": "七日签到第三天奖励",
    "Rate": 10000,
    "Team": 1002,
    "Type": 1,
    "Items": "[{\"id\":101,\"num\":300},{\"id\":110,\"num\":300}]",
    "AddData": ""
  },
  {
    "Id": 600004,
    "Desc": "七日签到第四天奖励",
    "Rate": 10000,
    "Team": 1003,
    "Type": 1,
    "Items": "[{\"id\":101,\"num\":400},{\"id\":110,\"num\":400}]",
    "AddData": ""
  },
  {
    "Id": 600005,
    "Desc": "七日签到第五天奖励",
    "Rate": 10000,
    "Team": 1004,
    "Type": 1,
    "Items": "[{\"id\":101,\"num\":500},{\"id\":110,\"num\":500}]",
    "AddData": ""
  },
  {
    "Id": 600006,
    "Desc": "七日签到第六天奖励",
    "Rate": 10000,
    "Team": 1005,
    "Type": 1,
    "Items": "[{\"id\":101,\"num\":600},{\"id\":110,\"num\":600}]",
    "AddData": ""
  },
  {
    "Id": 600007,
    "Desc": "七日签到第七天奖励",
    "Rate": 10000,
    "Team": 1006,
    "Type": 1,
    "Items": "[{\"id\":101,\"num\":700},{\"id\":110,\"num\":700}]",
    "AddData": ""
  },
  {
    "Id": 600008,
    "Desc": "",
    "Rate": 50,
    "Team": 1007,
    "Type": 2,
    "Items": "[{\"id\":350001,\"num\":1,\"rate\":50},{\"id\":350001,\"num\":1,\"rate\":50}]",
    "AddData": ""
  },
  {
    "Id": 600009,
    "Desc": "",
    "Rate": 50,
    "Team": 1008,
    "Type": 3,
    "Items": "[{\"id\":350001,\"num\":1,\"rate\":10000},{\"id\":350002,\"num\":1,\"rate\":50},{\"id\":350003,\"num\":1,\"rate\":50}]",
    "AddData": ""
  },
  {
    "Id": 600010,
    "Desc": "",
    "Rate": 50,
    "Team": 1009,
    "Type": 3,
    "Items": "[{\"id\":350001,\"num\":1,\"rate\":10000},{\"id\":600002,\"num\":1,\"rate\":10000}]",
    "AddData": ""
  }
]